{
  "version": "0.2",
  "language": "en",
  "globRoot": "./",
  "words": [],
  "dictionaryDefinitions": [
    {
      "name": "xiaozhi-words",
      "path": "./.cspell/words.txt",
      "addWords": true
    }
  ],
  "dictionaries": ["xiaozhi-words"],
  "ignorePaths": [
    "node_modules/**",
    "reports/jscpd",
    "**/dist/**",
    "dist/**",
    "docs/out/**",
    "**/coverage/**",
    ".git/**",
    "*.log",
    "**/tmp/**",
    "pnpm-lock.yaml",
    "CHANGELOG.md",
    "**/*.tsbuildinfo",
    ".cspell/**"
  ],
  "ignoreWords": [],
  "flagWords": []
}
